<?xml version="1.0" encoding="utf-8"?>
<LanguageData>

	<Nymphomaniac.degreeDatas.0.label>Нимфоман</Nymphomaniac.degreeDatas.0.label>
	<Nymphomaniac.degreeDatas.0.description>NAME любит секс и всегда хочет большего.</Nymphomaniac.degreeDatas.0.description>

	<Rapist.degreeDatas.0.label>Насильник</Rapist.degreeDatas.0.label>
	<Rapist.degreeDatas.0.description>Для NAME 'Нет!' это не ответ.</Rapist.degreeDatas.0.description>

	<Necrophiliac.degreeDatas.0.label>Некрофил</Necrophiliac.degreeDatas.0.label>
	<Necrophiliac.degreeDatas.0.description>Мертвые не говорят нет...</Necrophiliac.degreeDatas.0.description>

	<Zoophiliac.degreeDatas.0.label>Зоофил</Zoophiliac.degreeDatas.0.label>
	<Zoophiliac.degreeDatas.0.description>NAME любит дикую природу.</Zoophiliac.degreeDatas.0.description>
</LanguageData>